contswi/__init__.py
contswi/cli.py
contswi-0.1.5.dist-info/LICENSE
contswi-0.1.5.dist-info/METADATA
contswi-0.1.5.dist-info/WHEEL
contswi-0.1.5.dist-info/entry_points.txt
contswi-0.1.5.dist-info/top_level.txt
contswi-0.1.5.dist-info/RECORD
