Metadata-Version: 2.1
Name: contswi
Version: 0.1.5
Summary: A simple kubectl context switcher cli tool
Home-page: https://github.com/Savalinn/contswi
Author: Gabor Puskas
Author-email: pg@0r.hu
License: MIT
Classifier: Programming Language :: Python :: 3
Classifier: Programming Language :: Python :: 3.6
Classifier: Programming Language :: Python :: 3.7
Classifier: Programming Language :: Python :: 3.8
Classifier: Programming Language :: Python :: 3.9
Classifier: License :: OSI Approved :: MIT License
Classifier: Operating System :: POSIX :: Linux
Requires-Python: >=3.7
License-File: LICENSE
